LICENSE
MANIFEST.in
README.rst
requirements-docs.txt
requirements-test.txt
requirements.txt
setup.cfg
setup.py
src/tolerance/__init__.py
src/tolerance/decorators.py
src/tolerance/functional.py
src/tolerance/utils.py
src/tolerance.egg-info/PKG-INFO
src/tolerance.egg-info/SOURCES.txt
src/tolerance.egg-info/dependency_links.txt
src/tolerance.egg-info/top_level.txt
src/tolerance.egg-info/zip-safe