Metadata-Version: 1.1
Name: tolerance
Version: 0.1.0
Summary: A function decorator which makes a function tolerant (the function fail silently).
Home-page: https://github.com/lambdalisue/tolerance
Author: Alisue
Author-email: lambdalisue@hashnote.net
License: MIT
Download-URL: https://github.com/lambdalisue/tolerance/tarball/master
Keywords: function decorator,decorator,fail silently
Platform: UNKNOWN
Classifier: Development Status :: 3 - Alpha
Classifier: Intended Audience :: Developers
Classifier: License :: OSI Approved :: MIT License
Classifier: Programming Language :: Python
Classifier: Programming Language :: Python :: 3
